neoralab_sascorer/__init__.py
neoralab_sascorer/api.py
neoralab_sascorer/cli.py
neoralab_sascorer/fpscores.pkl.gz
neoralab_sascorer/sascorer.py
neoralab_sascorer/version.py
neoralab_sascorer-0.1.0.dist-info/licenses/LICENSE
neoralab_sascorer-0.1.0.dist-info/METADATA
neoralab_sascorer-0.1.0.dist-info/WHEEL
neoralab_sascorer-0.1.0.dist-info/entry_points.txt
neoralab_sascorer-0.1.0.dist-info/top_level.txt
neoralab_sascorer-0.1.0.dist-info/RECORD
