Metadata-Version: 2.4
Name: neoralab-sascorer
Version: 0.1.0
Summary: Synthetic accessibility scoring from RDKit Contrib SA_Score
Author: RDKit contributors
License: BSD-3-Clause
Classifier: Programming Language :: Python :: 3
Classifier: License :: OSI Approved :: BSD License
Classifier: Operating System :: OS Independent
Requires-Python: >=3.8
License-File: LICENSE
Requires-Dist: rdkit>=2025.9.3
Dynamic: license-file
